.gitlab-ci.yml
AUTHORS
ChangeLog
Pipfile
Pipfile.lock
README.md
app-checkout.yml
app.yml
conftest.py
requirements-dev.txt
requirements.txt
setup.cfg
setup.py
tox.ini
mailman2discourse/cmd.py
mailman2discourse/discourse.py
mailman2discourse/importer.py
mailman2discourse/mailman.py
mailman2discourse/retry.py
mailman2discourse.egg-info/PKG-INFO
mailman2discourse.egg-info/SOURCES.txt
mailman2discourse.egg-info/dependency_links.txt
mailman2discourse.egg-info/entry_points.txt
mailman2discourse.egg-info/not-zip-safe
mailman2discourse.egg-info/pbr.json
mailman2discourse.egg-info/requires.txt
mailman2discourse.egg-info/top_level.txt
tests/build-discourse
tests/conftest.py
tests/helpers_mailman.py
tests/test_cmd.py
tests/test_discourse.py
tests/test_importer.py
tests/test_mailman.py
tests/test_requirements.py
tests/test_retry.py
tests/data/greek/README.txt
tests/data/greek/config.pck
tests/data/instances/README.txt
tests/data/instances/config.pck
tests/data/mboxes/fake/one.mbox
tests/data/mboxes/fake/two.mbox.gz
tests/data/mboxes/ok/another-wrong-encoding.txt
tests/data/mboxes/ok/attachment-1.txt
tests/data/mboxes/ok/attachment-2.txt
tests/data/mboxes/ok/attachment-3.txt
tests/data/mboxes/ok/attachment-4.txt
tests/data/mboxes/ok/bad-subject-header.txt
tests/data/mboxes/ok/bad_content_type.txt
tests/data/mboxes/ok/bad_date_tz.txt
tests/data/mboxes/ok/bad_folding.txt
tests/data/mboxes/ok/cant_write_error_message.txt
tests/data/mboxes/ok/good.txt
tests/data/mboxes/ok/non-ascii-date-header.txt
tests/data/mboxes/ok/non-ascii-headers.txt
tests/data/mboxes/ok/payload-utf8-wrong.txt
tests/data/mboxes/ok/resent-date.txt
tests/data/mboxes/ok/strange-in-reply-to-header.txt
tests/data/mboxes/ok/unconvertable_message.txt
tests/data/mboxes/ok/unconvertable_msg-2.txt
tests/data/mboxes/ok/unixfrom-date.txt
tests/data/mboxes/ok/unknown-charset.txt
tests/data/mboxes/ok/wrong-in-reply-to-header.txt
tests/data/mboxes/skip/unicode_issue.txt
tests/data/regular/README.txt
tests/data/regular/config.pck