Metadata-Version: 2.1
Name: mailman2discourse
Version: 1.0.4
Summary: Convert mailman2 mailing lists into discourse categories
Home-page: https://lab.enough.community/discourse/mailman2discourse
Author: Enough Community
Author-email: contact@enough.community
License: AGPLv3+
Project-URL: Bug Tracker, https://lab.enough.community/discourse/mailman2discourse/issues
Project-URL: Documentation, https://lab.enough.community/discourse/mailman2discourse/-/blob/master/README.md
Project-URL: Source Code, https://lab.enough.community/discourse/mailman2discourse
Platform: UNKNOWN
Classifier: Development Status :: 4 - Beta
Classifier: Environment :: Console
Classifier: Intended Audience :: Developers
Classifier: Intended Audience :: Information Technology
Classifier: License :: OSI Approved :: GNU Affero General Public License v3 or later (AGPLv3+)
Classifier: Operating System :: OS Independent
Classifier: Programming Language :: Python :: 3
